setup.cfg
setup.py
dspl/__init__.py
dspl/validation.py
dspl/wrapper.py
dspl.egg-info/PKG-INFO
dspl.egg-info/SOURCES.txt
dspl.egg-info/dependency_links.txt
dspl.egg-info/requires.txt
dspl.egg-info/top_level.txt