Metadata-Version: 1.1
Name: dspl
Version: 0.0.13
Summary: Library for using in DS-Platform
Home-page: https://github.com/NV-27/dspl
Author: Nikita Varganov
Author-email: nikita.varganov.ml@gmail.com
License: MIT
Download-URL: https://github.com/NV-27/dspl/archive/0.0.13.tar.gz
Keywords: dspl,ds_platform,ds_template
Platform: UNKNOWN
Classifier: Development Status :: 3 - Alpha
Classifier: Programming Language :: Python :: 3.6
Classifier: Operating System :: OS Independent
